{
  "_class": "shapeGroup",
  "clippingMaskMode": 0,
  "do_objectID": "2FF3DD28-3875-4DC1-AC63-00FBD63371FB",
  "exportOptions": {
    "_class": "exportOptions",
    "exportFormats": [
    ],
    "includedLayerIds": [
    ],
    "layerOptions": 0,
    "shouldTrim": false
  },
  "frame": {
    "_class": "rect",
    "constrainProportions": false,
    "height": 14.0300809887168,
    "width": 20.97815784499972,
    "x": 0.3198120654897139,
    "y": 8.059358993693195
  },
  "hasClickThrough": false,
  "hasClippingMask": false,
  "isFlippedHorizontal": false,
  "isFlippedVertical": false,
  "isLocked": false,
  "isVisible": true,
  "layerListExpandedType": 0,
  "layers": [
    {
      "class": "shapePath",
      "id": "E7185258-A954-4859-9C2E-5B69C6E9F0E2"
    }
  ],
  "name": "Path 51",
  "nameIsFixed": false,
  "resizingConstraint": 63,
  "resizingType": 0,
  "rotation": 0,
  "shouldBreakMaskChain": false,
  "style": {
    "sharedObjectID": "821AE1D1-4E18-4C4E-8A81-BF047C0AF3D8"
  },
  "windingRule": 0
}