{
  "_class": "shapeGroup",
  "clippingMaskMode": 0,
  "do_objectID": "A8D98E8F-9499-4D25-9867-C8A2935E9ACF",
  "exportOptions": {
    "_class": "exportOptions",
    "exportFormats": [
    ],
    "includedLayerIds": [
    ],
    "layerOptions": 0,
    "shouldTrim": false
  },
  "frame": {
    "_class": "rect",
    "constrainProportions": false,
    "height": 5.783783783783822,
    "width": 5.578947368421037,
    "x": 6.263157894736651,
    "y": 28.37837837837833
  },
  "hasClickThrough": false,
  "hasClippingMask": false,
  "isFlippedHorizontal": false,
  "isFlippedVertical": false,
  "isLocked": false,
  "isVisible": true,
  "layerListExpandedType": 0,
  "layers": [
    {
      "class": "shapePath",
      "id": "EB1172A9-E7BE-4D9C-AFC7-12F73F969FB8"
    },
    {
      "class": "shapePath",
      "id": "61515D13-1F36-460F-BC0B-761AC3A1639E"
    }
  ],
  "name": "Oval 5 Copy 6",
  "nameIsFixed": false,
  "resizingConstraint": 63,
  "resizingType": 0,
  "rotation": 0,
  "shouldBreakMaskChain": false,
  "style": {
    "_class": "style",
    "blur": {
      "_class": "blur",
      "center": "{0.5, 0.5}",
      "isEnabled": false,
      "motionAngle": 0,
      "radius": 15.45454545454545,
      "type": 0
    },
    "borders": [
      {
        "_class": "border",
        "color": {
          "_class": "color",
          "alpha": 1,
          "blue": 0.592,
          "green": 0.592,
          "red": 0.592
        },
        "fillType": 0,
        "isEnabled": false,
        "position": 1,
        "thickness": 1.545454545454545
      }
    ],
    "endDecorationType": 0,
    "fills": [
      {
        "_class": "fill",
        "color": {
          "_class": "color",
          "alpha": 1,
          "blue": 0.2651797648288127,
          "green": 0.6387413309250043,
          "red": 0.9842155612244898
        },
        "fillType": 0,
        "isEnabled": true,
        "noiseIndex": 0,
        "noiseIntensity": 0,
        "patternFillType": 0,
        "patternTileScale": 1
      }
    ],
    "miterLimit": 10,
    "startDecorationType": 0
  },
  "windingRule": 0
}