{
  "_class": "group",
  "do_objectID": "28A1D802-048C-4DF9-9353-50CADC322B0B",
  "exportOptions": {
    "_class": "exportOptions",
    "exportFormats": [
    ],
    "includedLayerIds": [
    ],
    "layerOptions": 0,
    "shouldTrim": false
  },
  "frame": {
    "_class": "rect",
    "constrainProportions": false,
    "height": 72,
    "width": 144,
    "x": 0,
    "y": 0
  },
  "hasClickThrough": false,
  "isFlippedHorizontal": false,
  "isFlippedVertical": false,
  "isLocked": false,
  "isVisible": true,
  "layerListExpandedType": 0,
  "layers": [
    {
      "class": "shapeGroup",
      "id": "95CAE39E-5B6E-4BA7-9A5C-94BB46B6207E"
    },
    {
      "class": "group",
      "id": "68C6F7E5-2DDA-41C7-B878-A27BBBFA4ADD"
    },
    {
      "class": "group",
      "id": "B6A8BC7C-713C-4A65-8DE2-236F12B61734"
    },
    {
      "class": "group",
      "id": "AC52FF32-10B8-4FD4-853B-C2C4CF23AB78"
    },
    {
      "class": "text",
      "id": "248005E9-991A-4070-8AFA-2523B83F3BFB"
    },
    {
      "class": "group",
      "id": "9E5CC7F5-7028-4248-99C4-BB0D8EA96EFB"
    }
  ],
  "name": "elements/form/desk/date-picker/focused",
  "nameIsFixed": true,
  "resizingConstraint": 18,
  "resizingType": 0,
  "rotation": 0,
  "shouldBreakMaskChain": false,
  "style": {
    "_class": "style",
    "endDecorationType": 0,
    "miterLimit": 10,
    "startDecorationType": 0
  }
}