{
  "_class": "shapeGroup",
  "clippingMaskMode": 0,
  "do_objectID": "064C30FD-12DA-4379-93DB-74F977B88F62",
  "exportOptions": {
    "_class": "exportOptions",
    "do_objectID": "BC0087AA-735A-4062-A06C-67A25DB99B4C",
    "exportFormats": [
    ],
    "includedLayerIds": [
    ],
    "layerOptions": 0,
    "shouldTrim": false
  },
  "frame": {
    "_class": "rect",
    "constrainProportions": false,
    "do_objectID": "4078BDF0-1CBA-42F4-9FCC-CFFC8D024BB9",
    "height": 14.89655172413793,
    "width": 14.89655172413793,
    "x": 0,
    "y": 1.103448275862069
  },
  "hasClickThrough": false,
  "hasClippingMask": false,
  "isFlippedHorizontal": false,
  "isFlippedVertical": false,
  "isLocked": false,
  "isVisible": true,
  "layerListExpandedType": 0,
  "layers": [
    {
      "class": "shapePath",
      "id": "5C06E0B5-0652-4F33-9971-CB66686C2DC2"
    },
    {
      "class": "shapePath",
      "id": "9F279347-2D76-4191-8A5D-04F890E5CD7F"
    }
  ],
  "name": "Shape",
  "nameIsFixed": false,
  "resizingConstraint": 63,
  "resizingType": 0,
  "rotation": 0,
  "shouldBreakMaskChain": false,
  "style": {
    "_class": "style",
    "do_objectID": "E6BA2F5A-08CF-47EE-9376-0FBD0D56F9D3",
    "endDecorationType": 0,
    "fills": [
      {
        "_class": "fill",
        "color": {
          "_class": "color",
          "alpha": 1,
          "blue": 0.8156862745098039,
          "green": 0.7803921568627451,
          "red": 0.7568627450980392
        },
        "fillType": 0,
        "isEnabled": true,
        "noiseIndex": 0,
        "noiseIntensity": 0,
        "patternFillType": 1,
        "patternTileScale": 1
      }
    ],
    "miterLimit": 10,
    "startDecorationType": 0
  },
  "userInfo": {
    "com.animaapp.stc-sketch-plugin": {
      "kModelPropertiesKey": {
      }
    }
  },
  "windingRule": 0
}