{
  "_class": "shapeGroup",
  "clippingMaskMode": 0,
  "do_objectID": "B33ACBE7-071B-4930-9F8D-F23581A8716E",
  "exportOptions": {
    "_class": "exportOptions",
    "exportFormats": [
    ],
    "includedLayerIds": [
    ],
    "layerOptions": 0,
    "shouldTrim": false
  },
  "frame": {
    "_class": "rect",
    "constrainProportions": false,
    "height": 3.722113495464455,
    "width": 5.77548315215359,
    "x": 5.106124135177197,
    "y": 20.82536927952424
  },
  "hasClickThrough": false,
  "hasClippingMask": false,
  "isFlippedHorizontal": false,
  "isFlippedVertical": false,
  "isLocked": false,
  "isVisible": true,
  "layerListExpandedType": 0,
  "layers": [
    {
      "class": "shapePath",
      "id": "15245C2B-27D6-4B17-BED4-2E4741894B88"
    }
  ],
  "name": "Path 54",
  "nameIsFixed": false,
  "resizingConstraint": 63,
  "resizingType": 0,
  "rotation": 0,
  "shouldBreakMaskChain": false,
  "style": {
    "_class": "style",
    "borders": [
      {
        "_class": "border",
        "color": {
          "_class": "color",
          "alpha": 1,
          "blue": 0.592,
          "green": 0.592,
          "red": 0.592
        },
        "fillType": 0,
        "isEnabled": false,
        "position": 1,
        "thickness": 1
      }
    ],
    "do_objectID": "2ED6531A-D5BC-4F69-AFA4-AC09FC456B87",
    "endDecorationType": 0,
    "fills": [
      {
        "_class": "fill",
        "color": {
          "_class": "color",
          "alpha": 1,
          "blue": 0.6431372549019607,
          "green": 0.5764705882352941,
          "red": 0.5372549019607843
        },
        "fillType": 0,
        "isEnabled": true,
        "noiseIndex": 0,
        "noiseIntensity": 0,
        "patternFillType": 1,
        "patternTileScale": 1
      }
    ],
    "miterLimit": 10,
    "sharedObjectID": "C7918EDD-72FA-478D-BB42-B5BA168FB462",
    "startDecorationType": 0
  },
  "windingRule": 0
}