{
  "_class": "shapePath",
  "booleanOperation": -1,
  "do_objectID": "F972CEC2-50CC-4A23-AD4D-892359A05B3F",
  "edited": true,
  "exportOptions": {
    "_class": "exportOptions",
    "exportFormats": [
    ],
    "includedLayerIds": [
    ],
    "layerOptions": 0,
    "shouldTrim": false
  },
  "frame": {
    "_class": "rect",
    "constrainProportions": false,
    "height": 6.736842105263172,
    "width": 6.473684210526216,
    "x": 0,
    "y": 0
  },
  "isClosed": true,
  "isFlippedHorizontal": false,
  "isFlippedVertical": false,
  "isLocked": false,
  "isVisible": true,
  "layerListExpandedType": 0,
  "name": "Path",
  "nameIsFixed": false,
  "path": {
    "_class": "path",
    "isClosed": true,
    "pointRadiusBehaviour": 1,
    "points": [
      {
        "_class": "curvePoint",
        "cornerRadius": 0,
        "curveFrom": "{0.22182097288945168, 1}",
        "curveMode": 2,
        "curveTo": "{0.77817902711054832, 1}",
        "hasCurveFrom": true,
        "hasCurveTo": true,
        "point": "{0.5, 1}"
      },
      {
        "_class": "curvePoint",
        "cornerRadius": 0,
        "curveFrom": "{0, 0.22569468473219112}",
        "curveMode": 2,
        "curveTo": "{0, 0.77430531526780833}",
        "hasCurveFrom": true,
        "hasCurveTo": true,
        "point": "{0, 0.50000000000000056}"
      },
      {
        "_class": "curvePoint",
        "cornerRadius": 0,
        "curveFrom": "{0.77817902711054943, 0}",
        "curveMode": 2,
        "curveTo": "{0.2218209728894506, 0}",
        "hasCurveFrom": true,
        "hasCurveTo": true,
        "point": "{0.5, 0}"
      },
      {
        "_class": "curvePoint",
        "cornerRadius": 0,
        "curveFrom": "{1, 0.77430531526780833}",
        "curveMode": 2,
        "curveTo": "{1, 0.22569468473219112}",
        "hasCurveFrom": true,
        "hasCurveTo": true,
        "point": "{1, 0.50000000000000056}"
      }
    ]
  },
  "pointRadiusBehaviour": 1,
  "points": [
    {
      "_class": "curvePoint",
      "cornerRadius": 0,
      "curveFrom": "{0.22182097288945168, 1}",
      "curveMode": 2,
      "curveTo": "{0.77817902711054832, 1}",
      "hasCurveFrom": true,
      "hasCurveTo": true,
      "point": "{0.5, 1}"
    },
    {
      "_class": "curvePoint",
      "cornerRadius": 0,
      "curveFrom": "{0, 0.22569468473219112}",
      "curveMode": 2,
      "curveTo": "{0, 0.77430531526780833}",
      "hasCurveFrom": true,
      "hasCurveTo": true,
      "point": "{0, 0.50000000000000056}"
    },
    {
      "_class": "curvePoint",
      "cornerRadius": 0,
      "curveFrom": "{0.77817902711054943, 0}",
      "curveMode": 2,
      "curveTo": "{0.2218209728894506, 0}",
      "hasCurveFrom": true,
      "hasCurveTo": true,
      "point": "{0.5, 0}"
    },
    {
      "_class": "curvePoint",
      "cornerRadius": 0,
      "curveFrom": "{1, 0.77430531526780833}",
      "curveMode": 2,
      "curveTo": "{1, 0.22569468473219112}",
      "hasCurveFrom": true,
      "hasCurveTo": true,
      "point": "{1, 0.50000000000000056}"
    }
  ],
  "resizingConstraint": 63,
  "resizingType": 0,
  "rotation": 0,
  "shouldBreakMaskChain": false
}