{
  "_class": "shapeGroup",
  "clippingMaskMode": 0,
  "do_objectID": "13DB2276-A8CF-4753-8192-D3FC83ECBF6C",
  "exportOptions": {
    "_class": "exportOptions",
    "exportFormats": [
    ],
    "includedLayerIds": [
    ],
    "layerOptions": 0,
    "shouldTrim": false
  },
  "frame": {
    "_class": "rect",
    "constrainProportions": false,
    "height": 16,
    "width": 16,
    "x": 0,
    "y": 0
  },
  "hasClickThrough": false,
  "hasClippingMask": false,
  "isFlippedHorizontal": false,
  "isFlippedVertical": false,
  "isLocked": false,
  "isVisible": true,
  "layerListExpandedType": 0,
  "layers": [
    {
      "class": "shapePath",
      "id": "7CEAC24C-9B06-4755-9DC1-C1F07A4486BF"
    },
    {
      "class": "shapePath",
      "id": "526F3CB5-3993-4D0A-815D-84C31322D373"
    }
  ],
  "name": "Rectangle",
  "nameIsFixed": false,
  "resizingConstraint": 63,
  "resizingType": 0,
  "rotation": 0,
  "shouldBreakMaskChain": false,
  "style": {
    "sharedObjectID": "CB8ABEAA-A919-4549-9894-69B2408A78E3"
  },
  "windingRule": 0
}