{
  "_class": "shapeGroup",
  "clippingMaskMode": 0,
  "do_objectID": "E524D6EC-65B7-49C4-8802-2CED738D25D5",
  "exportOptions": {
    "_class": "exportOptions",
    "exportFormats": [
    ],
    "includedLayerIds": [
    ],
    "layerOptions": 0,
    "shouldTrim": false
  },
  "frame": {
    "_class": "rect",
    "constrainProportions": false,
    "height": 15.58518518518519,
    "width": 11.91111111111111,
    "x": 0,
    "y": 0.1185185185185183
  },
  "hasClickThrough": false,
  "hasClippingMask": false,
  "isFlippedHorizontal": false,
  "isFlippedVertical": false,
  "isLocked": false,
  "isVisible": true,
  "layerListExpandedType": 0,
  "layers": [
    {
      "class": "shapePath",
      "id": "04BA5ACD-F08E-4BD2-9BA6-51063B19D9CF"
    },
    {
      "class": "shapePath",
      "id": "9D3B1D72-0C3F-4633-82AA-C1A35CDFB288"
    },
    {
      "class": "shapePath",
      "id": "185245F2-03F2-4EA9-985E-9246090321DF"
    }
  ],
  "name": "Shape",
  "nameIsFixed": false,
  "resizingConstraint": 63,
  "resizingType": 0,
  "rotation": 0,
  "shouldBreakMaskChain": false,
  "style": {
    "sharedObjectID": "C7918EDD-72FA-478D-BB42-B5BA168FB462"
  },
  "userInfo": {
    "com.animaapp.stc-sketch-plugin": {
      "kModelPropertiesKey": {
      }
    }
  },
  "windingRule": 0
}