{
  "_class": "sharedStyle",
  "do_objectID": "4633FC51-4B11-49D7-BCC4-876332ADCC2C",
  "name": "color/secondary/secondary-cyan-light",
  "value": {
    "_class": "style",
    "borders": [
      {
        "_class": "border",
        "color": {
          "_class": "color",
          "alpha": 1,
          "blue": 0.592,
          "green": 0.592,
          "red": 0.592
        },
        "fillType": 0,
        "isEnabled": false,
        "position": 1,
        "thickness": 1
      }
    ],
    "endDecorationType": 0,
    "fills": [
      {
        "_class": "fill",
        "color": {
          "_class": "color",
          "alpha": 1,
          "blue": 0.9607843137254902,
          "green": 0.7568627450980392,
          "red": 0.4627450980392157
        },
        "fillType": 0,
        "isEnabled": true,
        "noiseIndex": 0,
        "noiseIntensity": 0,
        "patternFillType": 1,
        "patternTileScale": 1
      }
    ],
    "miterLimit": 10,
    "sharedObjectID": "4633FC51-4B11-49D7-BCC4-876332ADCC2C",
    "startDecorationType": 0
  }
}